urlexpander_test/__init__.py
urlexpander_test/core/__init__.py
urlexpander_test/core/api.py
urlexpander_test/core/constants.py
urlexpander_test/core/datasets.py
urlexpander_test/core/html_utils.py
urlexpander_test/core/tweet_utils.py
urlexpander_test-0.0.37.dist-info/LICENSE
urlexpander_test-0.0.37.dist-info/METADATA
urlexpander_test-0.0.37.dist-info/WHEEL
urlexpander_test-0.0.37.dist-info/top_level.txt
urlexpander_test-0.0.37.dist-info/RECORD
