Metadata-Version: 2.1
Name: urlexpander-test
Version: 0.0.37
Summary: urlExpander is a Python package for quickly and thoroughly expanding shortened URLs.
Home-page: https://github.com/SMAPPNYU/urlExpander
Author: leon yin
Author-email: 
License: MIT
Keywords: smapp social media unshorten expand link url
License-File: LICENSE
Requires-Dist: tldextract
Requires-Dist: pandas
Requires-Dist: numpy
Requires-Dist: tqdm
Requires-Dist: unshortenit
